pytbo/__init__.py
pytbo/bare.py
pytbo/errors.py
pytbo/types.py
pytbo-0.1.0.dist-info/DESCRIPTION.rst
pytbo-0.1.0.dist-info/METADATA
pytbo-0.1.0.dist-info/RECORD
pytbo-0.1.0.dist-info/WHEEL
pytbo-0.1.0.dist-info/metadata.json
pytbo-0.1.0.dist-info/top_level.txt
