Metadata-Version: 2.0
Name: pytbo
Version: 0.1.0
Summary: Python Telegram Bots made easy
Home-page: https://github.com/kostola/pytbo
Author: Alessandro Costa
Author-email: alecosta.me@gmail.com
License: Apache 2.0
Platform: UNKNOWN
Classifier: Development Status :: 3 - Alpha
Classifier: Intended Audience :: Developers
Classifier: Natural Language :: English
Classifier: License :: OSI Approved :: Apache Software License
Classifier: Programming Language :: Python
Classifier: Programming Language :: Python :: 2.7
Classifier: Programming Language :: Python :: 3
Classifier: Programming Language :: Python :: 3.3
Classifier: Programming Language :: Python :: 3.4
Classifier: Programming Language :: Python :: 3.5
Requires-Dist: requests (<3.0.0,>=2.1.0)
Requires-Dist: requests-toolbelt (<0.7.0,>=0.6.0)
